Workbook

Sheet Business Ideas
A1: Category No. | B1: Category | C1: Subcategory No. | D1: Subcategory Business Idea | E1: SEO Keywords | F1: Target Audience | G1: Starting Budget | H1: Short Description
A2: 1 | B2: Regional Heritage Food Processing | C2: 1 | D2: Millet Based Snack Packaging Business Ideas | E2: millet snack business ideas, healthy snack startup India, regional food business | F2: Homemakers in tier-2 cities | G2: Under ₹10,000 | H2: Packaging and selling traditional millet snacks through local grocery stores and WhatsApp orders.
A3: 1 | B3: Regional Heritage Food Processing | C3: 2 | D3: Cold Pressed Mustard Oil Bottling Business Ideas | E3: cold pressed oil business ideas, mustard oil startup India, organic oil business | F3: Farmers and rural entrepreneurs | G3: Under ₹50,000 | H3: Sourcing raw mustard seeds, cold pressing locally, and bottling for direct consumer sales.
A4: 1 | B4: Regional Heritage Food Processing | C4: 3 | D4: Traditional Jaggery Block Flavouring Business Ideas | E4: jaggery business ideas, flavoured jaggery startup India, organic sweetener business | F4: Rural women self help groups | G4: Under ₹10,000 | H4: Infusing local jaggery with dry fruits and spices for niche retail packaging.
A5: 1 | B5: Regional Heritage Food Processing | C5: 4 | D5: Dehydrated Onion Garlic Flake Business Ideas | E5: dehydrated vegetable business ideas, onion flake startup India, food processing | F5: Small scale agro entrepreneurs | G5: Under ₹50,000 | H5: Sun-drying or machine-drying onions and garlic for bulk supply to restaurants.
A6: 1 | B6: Regional Heritage Food Processing | C6: 5 | D6: Handmade Papad Rolling Agency Business Ideas | E6: papad making business ideas, homemade papad startup India, traditional food business | F6: Homemakers in semi-urban areas | G6: Under ₹1,000 | H6: Managing a network of women rolling traditional papads from home for bulk distribution.
A7: 1 | B7: Regional Heritage Food Processing | C7: 6 | D7: Indigenous Rice Variety Packaging Business Ideas | E7: organic rice business ideas, native rice startup India, heritage food business | F7: Agri-grads in rural towns | G7: Under ₹10,000 | H7: Cleaning, grading, and vacuum-packing native regional rice varieties for urban buyers.
A8: 1 | B8: Regional Heritage Food Processing | C8: 7 | D8: Traditional Ghee Refining & Packaging Business Ideas | E8: pure ghee business ideas, homemade ghee startup India, dairy business | F8: Rural dairy farmers | G8: Under ₹50,000 | H8: Producing traditional bilona cow ghee and selling directly to urban health-conscious consumers.
A9: 1 | B9: Regional Heritage Food Processing | C9: 8 | D9: Spiced Buttermilk Mix Packet Business Ideas | E9: chaas masala business ideas, instant drink startup India, beverage business | F9: Small scale food vendors | G9: Under ₹1,000 | H9: Blending dried spices and salt into ready-to-mix buttermilk sachets for local grocery shops.
A10: 1 | B10: Regional Heritage Food Processing | C10: 9 | D10: Handcrafted Herbal Salt Production Business Ideas | E10: herbal salt business ideas, flavored salt startup India, gourmet food business | F10: Culinary enthusiasts in metros | G10: Under ₹1,000 | H10: Mixing Himalayan pink salt with dried local herbs and spices for gourmet retail.
A11: 1 | B11: Regional Heritage Food Processing | C11: 10 | D11: Malted Ragi Health Drink Powder Business Ideas | E11: ragi malt business ideas, health drink startup India, baby food business | F11: Homemakers with nutrition background | G11: Under ₹10,000 | H11: Sprouting, roasting, and grinding ragi into nutritious health drink mixes for children.
A12: 2 | B12: Cloud Kitchen and Specialized Tiffin Operations | C12: 1 | D12: Diabetic Friendly Tiffin Delivery Business Ideas | E12: diabetic tiffin business ideas, low GI meal startup India, health food delivery | F12: Home chefs with nutrition training | G12: Under ₹10,000 | H12: Preparing and delivering calorie-counted low-glycemic meals to working professionals with diabetes.
A13: 2 | B13: Cloud Kitchen and Specialized Tiffin Operations | C13: 2 | D13: Hostel Student Home Food Tiffin Business Ideas | E13: student tiffin business ideas, mess service startup India, budget food delivery | F13: Homemakers near college hubs | G13: Under ₹10,000 | H13: Cooking affordable, homely vegetarian meals for out-of-town college students.
... A1001: 100 | B1001: Voice Search SEO for Regional Businesses | C1001: 10 | D1001: Smart Speaker Local Business Directory Submission Service Business Ideas | E1001: smart speaker SEO business ideas, startup India | F1001: Tech marketers | G1001: Under ₹1,000 | H1001: Submitting local business data to smart assistant voice directories and map nodes.

Sheet Categories
A1: Category No. | B1: Category | C1: Subcategories
A2: 1 | B2: Regional Heritage Food Processing | C2: =COUNTIF('Business Ideas'!B:B,B2)
A3: 2 | B3: Cloud Kitchen and Specialized Tiffin Operations | C3: =COUNTIF('Business Ideas'!B:B,B3)
A4: 3 | B4: Ethnic Snack and Confectionery Manufacturing | C4: =COUNTIF('Business Ideas'!B:B,B4)
A5: 4 | B5: Organic Health Food and Dietary Supplements | C5: =COUNTIF('Business Ideas'!B:B,B5)
A6: 5 | B6: Specialty Beverage and Herbal Tea Blending | C6: =COUNTIF('Business Ideas'!B:B,B6)
A7: 6 | B7: Handloom Textile Restoration and Weaving | C7: =COUNTIF('Business Ideas'!B:B,B7)
A8: 7 | B8: Traditional Terracotta and Pottery Crafts | C8: =COUNTIF('Business Ideas'!B:B,B8)
A9: 8 | B9: Eco Friendly Bamboo and Cane Utility Products | C9: =COUNTIF('Business Ideas'!B:B,B9)
A10: 9 | B10: Resin Art and Custom Home Decor | C10: =COUNTIF('Business Ideas'!B:B,B10)
A11: 10 | B11: Religious Puja Kits and Festival Artifacts | C11: =COUNTIF('Business Ideas'!B:B,B11)
A12: 11 | B12: Technical Documentation and API Copywriting | C12: =COUNTIF('Business Ideas'!B:B,B12)
A13: 12 | B13: Regional Language Legal Translation | C13: =COUNTIF('Business Ideas'!B:B,B13)
... A101: 100 | B101: Voice Search SEO for Regional Businesses | C101: =COUNTIF('Business Ideas'!B:B,B101)
